CHANGES.rst
CONTRIBUTORS.rst
DEVELOP.rst
LICENSE.GPL
LICENSE.rst
MANIFEST.in
README.rst
setup.cfg
setup.py
docs/index.rst
src/collective/__init__.py
src/collective.eeafaceted.layoutwidget.egg-info/PKG-INFO
src/collective.eeafaceted.layoutwidget.egg-info/SOURCES.txt
src/collective.eeafaceted.layoutwidget.egg-info/dependency_links.txt
src/collective.eeafaceted.layoutwidget.egg-info/namespace_packages.txt
src/collective.eeafaceted.layoutwidget.egg-info/not-zip-safe
src/collective.eeafaceted.layoutwidget.egg-info/requires.txt
src/collective.eeafaceted.layoutwidget.egg-info/top_level.txt
src/collective/eeafaceted/__init__.py
src/collective/eeafaceted/layoutwidget/__init__.py
src/collective/eeafaceted/layoutwidget/configure.zcml
src/collective/eeafaceted/layoutwidget/events.py
src/collective/eeafaceted/layoutwidget/faceted.py
src/collective/eeafaceted/layoutwidget/interfaces.py
src/collective/eeafaceted/layoutwidget/layout.pt
src/collective/eeafaceted/layoutwidget/layout.py
src/collective/eeafaceted/layoutwidget/query.py
src/collective/eeafaceted/layoutwidget/setuphandlers.py
src/collective/eeafaceted/layoutwidget/vocabulary.py
src/collective/eeafaceted/layoutwidget/locales/collective.eeafaceted.layoutwidget.pot
src/collective/eeafaceted/layoutwidget/locales/update.sh
src/collective/eeafaceted/layoutwidget/profiles/default/metadata.xml
src/collective/eeafaceted/layoutwidget/profiles/default/registry.xml
src/collective/eeafaceted/layoutwidget/resources/layout-edit.css
src/collective/eeafaceted/layoutwidget/resources/layout-edit.js
src/collective/eeafaceted/layoutwidget/resources/layout-view.css
src/collective/eeafaceted/layoutwidget/resources/layout-view.js